verspec/__init__.py
verspec/basespecifier.py
verspec/baseversion.py
verspec/infinity.py
verspec/loose.py
verspec/python.py
verspec-0.1.0.dist-info/LICENSE
verspec-0.1.0.dist-info/LICENSE.APACHE
verspec-0.1.0.dist-info/LICENSE.BSD
verspec-0.1.0.dist-info/METADATA
verspec-0.1.0.dist-info/WHEEL
verspec-0.1.0.dist-info/top_level.txt
verspec-0.1.0.dist-info/RECORD
