Metadata-Version: 2.1
Name: verspec
Version: 0.1.0
Summary: Flexible version handling
Home-page: https://github.com/jimporter/verspec
Author: Jim Porter
Author-email: itsjimporter@gmail.com
License: BSD 2-Clause or Apache-2.0
Keywords: version handling
Platform: UNKNOWN
Classifier: Development Status :: 3 - Alpha
Classifier: Intended Audience :: Developers
Classifier: License :: OSI Approved :: Apache Software License
Classifier: License :: OSI Approved :: BSD License
Classifier: Programming Language :: Python :: 3
Classifier: Programming Language :: Python :: 3.6
Classifier: Programming Language :: Python :: 3.7
Classifier: Programming Language :: Python :: 3.8
Provides-Extra: test
